isal/__init__.py
isal/_isal.cpython-313-aarch64-linux-gnu.so
isal/_isal.pyi
isal/_version.py
isal/_version.pyi
isal/igzip.py
isal/igzip_lib.cpython-313-aarch64-linux-gnu.so
isal/igzip_lib.pyi
isal/igzip_threaded.py
isal/isal_zlib.cpython-313-aarch64-linux-gnu.so
isal/isal_zlib.pyi
isal/py.typed
isal/isa-l/LICENSE
isal/isa-l/README.md
isal/isa-l/Release_notes.txt
isal-1.8.0.dist-info/METADATA
isal-1.8.0.dist-info/WHEEL
isal-1.8.0.dist-info/top_level.txt
isal-1.8.0.dist-info/RECORD
isal-1.8.0.dist-info/licenses/LICENSE
