Metadata-Version: 2.4
Name: isal
Version: 1.8.0
Summary: Faster zlib and gzip compatible compression and decompression by providing python bindings for the ISA-L ibrary.
Author: Leiden University Medical Center
Author-email: r.h.p.vorderman@lumc.nl
License-Expression: PSF-2.0
Project-URL: homepage, https://github.com/pycompression/python-isal
Project-URL: documentation, https://python-isal.readthedocs.io
Keywords: isal,isa-l,compression,deflate,gzip,igzip
Classifier: Programming Language :: Python :: 3 :: Only
Classifier: Programming Language :: Python :: 3
Classifier: Programming Language :: Python :: 3.10
Classifier: Programming Language :: Python :: 3.11
Classifier: Programming Language :: Python :: 3.12
Classifier: Programming Language :: Python :: 3.13
Classifier: Programming Language :: Python :: 3.14
Classifier: Programming Language :: Python :: Implementation :: CPython
Classifier: Programming Language :: Python :: Implementation :: PyPy
Classifier: Programming Language :: C
Classifier: Development Status :: 5 - Production/Stable
Classifier: Topic :: System :: Archiving :: Compression
Classifier: Operating System :: POSIX :: Linux
Classifier: Operating System :: MacOS
Classifier: Operating System :: Microsoft :: Windows
Requires-Python: >=3.9
License-File: LICENSE
Dynamic: license-file
